<?xml version="1.0" encoding="UTF-8"?>


<?eAIP-locales ../locales.xml?>
<e:ENR-4.4 id = "ENR-4.4" xmlns:x = "http://www.w3.org/1999/xhtml" xmlns:e = "http://www.eurocontrol.int/xmlns/AIM/eAIP" xmlns:xlink = "http://www.w3.org/1999/xlink"><?FM MARKER [FrameAPS Content] PM-0.1,557313,1595223?>
<e:Title id = "ENR440603081427571">NAME-CODE DESIGNATORS FOR SIGNIFICANT POINTS</e:Title><e:Designated-point-table id = "ENR442012013111413806710000" Updated = "Inserted" Updated-ref = "GEN022012011013121309680000">
<e:Designated-point id = "ABETI">
<e:Designated-point-ident id = "ENR441004131136371">ABETI</e:Designated-point-ident>
<e:Latitude id = "ABETI-LAT">474040N</e:Latitude>
<e:Longitude id = "ABETI-LONG">0170046E</e:Longitude></e:Designated-point>
<e:Designated-point id = "ABONY">
<e:Designated-point-ident id = "ENR441004131136375">ABONY</e:Designated-point-ident>
<e:Latitude id = "ABONY-LAT">471615N</e:Latitude>
<e:Longitude id = "ABONY-LONG">0195845E</e:Longitude></e:Designated-point>
<e:Designated-point id = "ABULI">
<e:Designated-point-ident id = "ENR4309022514243218">ABULI</e:Designated-point-ident>
<e:Latitude id = "ABULI-LAT">482903N</e:Latitude>
<e:Longitude id = "ABULI-LONG">0202912E</e:Longitude></e:Designated-point>
<e:Designated-point id = "AGMAS">
<e:Designated-point-ident id = "ENR441004131136379">AGMAS</e:Designated-point-ident>
<e:Latitude id = "AGMAS-LAT">472903N</e:Latitude>
<e:Longitude id = "AGMAS-LONG">0194130E</e:Longitude></e:Designated-point>
<e:Designated-point id = "ALAMU">
<e:Designated-point-ident id = "ENR4309022514243225">ALAMU</e:Designated-point-ident>
<e:Latitude id = "ALAMU-LAT">474413N</e:Latitude>
<e:Longitude id = "ALAMU-LONG">0181948E</e:Longitude></e:Designated-point>
<e:Designated-point id = "AMRAX">
<e:Designated-point-ident id = "ENR4309022514243228">AMRAX</e:Designated-point-ident>
<e:Latitude id = "AMRAX-LAT">480529N</e:Latitude>
<e:Longitude id = "AMRAX-LONG">0192158E</e:Longitude></e:Designated-point>
<e:Designated-point id = "ARSIN">
<e:Designated-point-ident id = "ENR4410041311363713">ARSIN</e:Designated-point-ident>
<e:Latitude id = "ARSIN-LAT">473402N</e:Latitude>
<e:Longitude id = "ARSIN-LONG">0164513E</e:Longitude></e:Designated-point>
<e:Designated-point id = "BABIT">
<e:Designated-point-ident id = "ENR4410041311363717">BABIT</e:Designated-point-ident>
<e:Latitude id = "BABIT-LAT">455554N</e:Latitude>
<e:Longitude id = "BABIT-LONG">0185544E</e:Longitude></e:Designated-point>
<e:Designated-point id = "BABOX">
<e:Designated-point-ident id = "ENR4410041311363721">BABOX</e:Designated-point-ident>
<e:Latitude id = "BABOX-LAT">465345N</e:Latitude>
<e:Longitude id = "BABOX-LONG">0194059E</e:Longitude></e:Designated-point>
<e:Designated-point id = "BADOR">
<e:Designated-point-ident id = "ENR4410041311363725">BADOR</e:Designated-point-ident>
<e:Latitude id = "BADOR-LAT">473425N</e:Latitude>
<e:Longitude id = "BADOR-LONG">0220629E</e:Longitude></e:Designated-point>
<e:Designated-point id = "BADOV">
<e:Designated-point-ident id = "ENR4410041311363730">BADOV</e:Designated-point-ident>
<e:Latitude id = "BADOV-LAT">480116N</e:Latitude>
<e:Longitude id = "BADOV-LONG">0184857E</e:Longitude></e:Designated-point>
<e:Designated-point id = "BALAP">
<e:Designated-point-ident id = "ENR4309022514243246">BALAP</e:Designated-point-ident>
<e:Latitude id = "BALAP-LAT">480405N</e:Latitude>
<e:Longitude id = "BALAP-LONG">0191500E</e:Longitude></e:Designated-point>
<e:Designated-point id = "BALUX">
<e:Designated-point-ident id = "ENR4410041311363738">BALUX</e:Designated-point-ident>
<e:Latitude id = "BALUX-LAT">472027N</e:Latitude>
<e:Longitude id = "BALUX-LONG">0190746E</e:Longitude></e:Designated-point>
<e:Designated-point id = "BAREB">
<e:Designated-point-ident id = "ENR4410041311363742">BAREB</e:Designated-point-ident>
<e:Latitude id = "BAREB-LAT">454446N</e:Latitude>
<e:Longitude id = "BAREB-LONG">0182448E</e:Longitude></e:Designated-point>
<e:Designated-point id = "BEGLA">
<e:Designated-point-ident id = "ENR4410041311363746">BEGLA</e:Designated-point-ident>
<e:Latitude id = "BEGLA-LAT">474951N</e:Latitude>
<e:Longitude id = "BEGLA-LONG">0170652E</e:Longitude></e:Designated-point>
<e:Designated-point id = "BINKU">
<e:Designated-point-ident id = "ENR4410041311363750">BINKU</e:Designated-point-ident>
<e:Latitude id = "BINKU-LAT">465534N</e:Latitude>
<e:Longitude id = "BINKU-LONG">0202733E</e:Longitude></e:Designated-point>
<e:Designated-point id = "BOKSI">
<e:Designated-point-ident id = "ENR4410041311363754">BOKSI</e:Designated-point-ident>
<e:Latitude id = "BOKSI-LAT">463807N</e:Latitude>
<e:Longitude id = "BOKSI-LONG">0194951E</e:Longitude></e:Designated-point>
<e:Designated-point id = "BUDOP">
<e:Designated-point-ident id = "ENR4309022514243261">BUDOP</e:Designated-point-ident>
<e:Latitude id = "BUDOP-LAT">464115N</e:Latitude>
<e:Longitude id = "BUDOP-LONG">0212948E</e:Longitude></e:Designated-point>
<e:Designated-point id = "DEGET">
<e:Designated-point-ident id = "ENR4410041311363758">DEGET</e:Designated-point-ident>
<e:Latitude id = "DEGET-LAT">462937N</e:Latitude>
<e:Longitude id = "DEGET-LONG">0211602E</e:Longitude></e:Designated-point>
<e:Designated-point id = "DEMOP">
<e:Designated-point-ident id = "ENR4309022514243267">DEMOP</e:Designated-point-ident>
<e:Latitude id = "DEMOP-LAT">481029N</e:Latitude>
<e:Longitude id = "DEMOP-LONG">0200325E</e:Longitude></e:Designated-point>
<e:Designated-point id = "DIMLO">
<e:Designated-point-ident id = "ENR4410041311363762"><?FM MARKER [FrameAPS Content] CM-1.1,262144,655360?>DIMLO</e:Designated-point-ident>
<e:Latitude id = "DIMLO-LAT">464101N</e:Latitude>
<e:Longitude id = "DIMLO-LONG">0162522E</e:Longitude></e:Designated-point>
<e:Designated-point id = "DODAR">
<e:Designated-point-ident id = "ENR4410041311363770">DODAR</e:Designated-point-ident>
<e:Latitude id = "DODAR-LAT">471252N</e:Latitude>
<e:Longitude id = "DODAR-LONG">0193139E</e:Longitude></e:Designated-point>
<e:Designated-point id = "EBORO">
<e:Designated-point-ident id = "ENR4410041311363774">EBORO</e:Designated-point-ident>
<e:Latitude id = "EBORO-LAT">462121N</e:Latitude>
<e:Longitude id = "EBORO-LONG">0195915E</e:Longitude></e:Designated-point>
<e:Designated-point id = "EPARI">
<e:Designated-point-ident id = "ENR4410041311363778">EPARI</e:Designated-point-ident>
<e:Latitude id = "EPARI-LAT">474111N</e:Latitude>
<e:Longitude id = "EPARI-LONG">0185841E</e:Longitude></e:Designated-point>
<e:Designated-point id = "ERGOM">
<e:Designated-point-ident id = "ENR4309022514243284">ERGOM</e:Designated-point-ident>
<e:Latitude id = "ERGOM-LAT">474830N</e:Latitude>
<e:Longitude id = "ERGOM-LONG">0184359E</e:Longitude></e:Designated-point>
<e:Designated-point id = "ERLOS">
<e:Designated-point-ident id = "ENR4410041311363782">ERLOS</e:Designated-point-ident>
<e:Latitude id = "ERLOS-LAT">470403N</e:Latitude>
<e:Longitude id = "ERLOS-LONG">0191630E</e:Longitude></e:Designated-point>
<e:Designated-point id = "EVAXI">
<e:Designated-point-ident id = "ENR4410041311363786">EVAXI</e:Designated-point-ident>
<e:Latitude id = "EVAXI-LAT">474640N</e:Latitude>
<e:Longitude id = "EVAXI-LONG">0170602E</e:Longitude></e:Designated-point>
<e:Designated-point id = "GELKA">
<e:Designated-point-ident id = "ENR4410041311363790">GELKA</e:Designated-point-ident>
<e:Latitude id = "GELKA-LAT">480605N</e:Latitude>
<e:Longitude id = "GELKA-LONG">0201359E</e:Longitude></e:Designated-point>
<e:Designated-point id = "GIGOR">
<e:Designated-point-ident id = "ENR4410041311363794">GIGOR</e:Designated-point-ident>
<e:Latitude id = "GIGOR-LAT">474534N</e:Latitude>
<e:Longitude id = "GIGOR-LONG">0174036E</e:Longitude></e:Designated-point>
<e:Designated-point id = "GILEP">
<e:Designated-point-ident id = "ENR4410041311363798">GILEP</e:Designated-point-ident>
<e:Latitude id = "GILEP-LAT">472900N</e:Latitude>
<e:Longitude id = "GILEP-LONG">0181532E</e:Longitude></e:Designated-point>
<e:Designated-point id = "GITAS">
<e:Designated-point-ident id = "ENR44100413113637102">GITAS</e:Designated-point-ident>
<e:Latitude id = "GITAS-LAT">470317N</e:Latitude>
<e:Longitude id = "GITAS-LONG">0181027E</e:Longitude></e:Designated-point>
<e:Designated-point id = "GOTAR">
<e:Designated-point-ident id = "ENR43090225142432107">GOTAR</e:Designated-point-ident>
<e:Latitude id = "GOTAR-LAT">465952N</e:Latitude>
<e:Longitude id = "GOTAR-LONG">0161329E</e:Longitude></e:Designated-point>
<e:Designated-point id = "INVED">
<e:Designated-point-ident id = "ENR442010121310003600460000">INVED</e:Designated-point-ident>
<e:Latitude id = "INVED-LAT">460928N</e:Latitude>
<e:Longitude id = "INVED-LONG">0202405E</e:Longitude></e:Designated-point>
<e:Designated-point id = "KARIL">
<e:Designated-point-ident id = "ENR44100413113637106">KARIL</e:Designated-point-ident>
<e:Latitude id = "KARIL-LAT">474738N</e:Latitude>
<e:Longitude id = "KARIL-LONG">0222632E</e:Longitude></e:Designated-point>
<e:Designated-point id = "KEKED">
<e:Designated-point-ident id = "ENR44100413113637110">KEKED</e:Designated-point-ident>
<e:Latitude id = "KEKED-LAT">483123N</e:Latitude>
<e:Longitude id = "KEKED-LONG">0211729E</e:Longitude></e:Designated-point>
<e:Designated-point id = "KENIN">
<e:Designated-point-ident id = "ENR44100413113637114">KENIN</e:Designated-point-ident>
<e:Latitude id = "KENIN-LAT">482142N</e:Latitude>
<e:Longitude id = "KENIN-LONG">0215538E</e:Longitude></e:Designated-point>
<e:Designated-point id = "KEROP">
<e:Designated-point-ident id = "ENR43090225142432119">KEROP</e:Designated-point-ident>
<e:Latitude id = "KEROP-LAT">461104N</e:Latitude>
<e:Longitude id = "KEROP-LONG">0194148E</e:Longitude></e:Designated-point>
<e:Designated-point id = "KOPRY">
<e:Designated-point-ident id = "ENR44100413113637122">KOPRY</e:Designated-point-ident>
<e:Latitude id = "KOPRY-LAT">461425N</e:Latitude>
<e:Longitude id = "KOPRY-LONG">0165746E</e:Longitude></e:Designated-point>
<e:Designated-point id = "KOVEK">
<e:Designated-point-ident id = "ENR44100413113637126">KOVEK</e:Designated-point-ident>
<e:Latitude id = "KOVEK-LAT">475050N</e:Latitude>
<e:Longitude id = "KOVEK-LONG">0203010E</e:Longitude></e:Designated-point>
<e:Designated-point id = "KUNET">
<e:Designated-point-ident id = "ENR44100413113637130">KUNET</e:Designated-point-ident>
<e:Latitude id = "KUNET-LAT">475648N</e:Latitude>
<e:Longitude id = "KUNET-LONG">0171935E</e:Longitude></e:Designated-point>
<e:Designated-point id = "LITKU">
<e:Designated-point-ident id = "ENR43090225142432131">LITKU</e:Designated-point-ident>
<e:Latitude id = "LITKU-LAT">481350N</e:Latitude>
<e:Longitude id = "LITKU-LONG">0193555E</e:Longitude></e:Designated-point>
<e:Designated-point id = "LONLA">
<e:Designated-point-ident id = "ENR44100413113637134">LONLA</e:Designated-point-ident>
<e:Latitude id = "LONLA-LAT">482024N</e:Latitude>
<e:Longitude id = "LONLA-LONG">0221911E</e:Longitude></e:Designated-point>
<e:Designated-point id = "MAVIR">
<e:Designated-point-ident id = "ENR44100413113637142"><?FM MARKER [FrameAPS Content] CM-2.1,262144,655360?>MAVIR</e:Designated-point-ident>
<e:Latitude id = "MAVIR-LAT">462354N</e:Latitude>
<e:Longitude id = "MAVIR-LONG">0194931E</e:Longitude></e:Designated-point>
<e:Designated-point id = "MEGIK" Updated = "Inserted" Updated-ref = "GEN022012011013121309680000">
<e:Designated-point-ident><e:Inserted id = "ENR442012020108565907340002" Updated = "Inserted" Updated-ref = "GEN022012011013121309680000" class = "Designated-point">MEGIK</e:Inserted></e:Designated-point-ident>
<e:Latitude id = "-LAT"><e:Inserted id = "ENR442012020108565907500000" Updated = "Inserted" Updated-ref = "GEN022012011013121309680000">471230N</e:Inserted></e:Latitude>
<e:Longitude id = "-LONG"><e:Inserted id = "ENR442012020108565907500001" Updated = "Inserted" Updated-ref = "GEN022012011013121309680000">0215140E</e:Inserted></e:Longitude></e:Designated-point>
<e:Designated-point id = "MIRLU">
<e:Designated-point-ident id = "ENR44100413113637150">MIRLU</e:Designated-point-ident>
<e:Latitude id = "MIRLU-LAT">475604N</e:Latitude>
<e:Longitude id = "MIRLU-LONG">0170830E</e:Longitude></e:Designated-point>
<e:Designated-point id = "MOPUG">
<e:Designated-point-ident id = "ENR44100413113637158">MOPUG</e:Designated-point-ident>
<e:Latitude id = "MOPUG-LAT">460949N</e:Latitude>
<e:Longitude id = "MOPUG-LONG">0204229E</e:Longitude></e:Designated-point>
<e:Designated-point id = "NALAG">
<e:Designated-point-ident id = "ENR44100413113637162">NALAG</e:Designated-point-ident>
<e:Latitude id = "NALAG-LAT">480233N</e:Latitude>
<e:Longitude id = "NALAG-LONG">0194557E</e:Longitude></e:Designated-point>
<e:Designated-point id = "NALOX">
<e:Designated-point-ident id = "ENR44100413113637166">NALOX</e:Designated-point-ident>
<e:Latitude id = "NALOX-LAT">465211N</e:Latitude>
<e:Longitude id = "NALOX-LONG">0164912E</e:Longitude></e:Designated-point>
<e:Designated-point id = "NARKA">
<e:Designated-point-ident id = "ENR44100413113637170">NARKA</e:Designated-point-ident>
<e:Latitude id = "NARKA-LAT">471454N</e:Latitude>
<e:Longitude id = "NARKA-LONG">0215136E</e:Longitude></e:Designated-point>
<e:Designated-point id = "NIKAB">
<e:Designated-point-ident id = "ENR44100413113637174">NIKAB</e:Designated-point-ident>
<e:Latitude id = "NIKAB-LAT">463709N</e:Latitude>
<e:Longitude id = "NIKAB-LONG">0173244E</e:Longitude></e:Designated-point>
<e:Designated-point id = "NORAH">
<e:Designated-point-ident id = "ENR44100413113637178">NORAH</e:Designated-point-ident>
<e:Latitude id = "NORAH-LAT">473658N</e:Latitude>
<e:Longitude id = "NORAH-LONG">0194829E</e:Longitude></e:Designated-point>
<e:Designated-point id = "NUBRA">
<e:Designated-point-ident id = "ENR44100413113637182">NUBRA</e:Designated-point-ident>
<e:Latitude id = "NUBRA-LAT">475200N</e:Latitude>
<e:Longitude id = "NUBRA-LONG">0173000E</e:Longitude></e:Designated-point>
<e:Designated-point id = "OKORA">
<e:Designated-point-ident id = "ENR44100413113637186">OKORA</e:Designated-point-ident>
<e:Latitude id = "OKORA-LAT">464559N</e:Latitude>
<e:Longitude id = "OKORA-LONG">0182217E</e:Longitude></e:Designated-point>
<e:Designated-point id = "OLATI">
<e:Designated-point-ident id = "ENR44100413113637190">OLATI</e:Designated-point-ident>
<e:Latitude id = "OLATI-LAT">465914N</e:Latitude>
<e:Longitude id = "OLATI-LONG">0172845E</e:Longitude></e:Designated-point>
<e:Designated-point id = "OSLEN" Updated = "No">
<e:Designated-point-ident id = "ENR44100413113637194">OSLEN</e:Designated-point-ident>
<e:Latitude id = "OSLEN-LAT">464336N</e:Latitude>
<e:Longitude id = "OSLEN-LONG">0202145E</e:Longitude></e:Designated-point>
<e:Designated-point id = "PATAK">
<e:Designated-point-ident id = "ENR44100413113637202">PATAK</e:Designated-point-ident>
<e:Latitude id = "PATAK-LAT">480423N</e:Latitude>
<e:Longitude id = "PATAK-LONG">0190738E</e:Longitude></e:Designated-point>
<e:Designated-point id = "PARAK">
<e:Designated-point-ident id = "ENR43090225142432179">PARAK</e:Designated-point-ident>
<e:Latitude id = "PARAK-LAT">460950N</e:Latitude>
<e:Longitude id = "PARAK-LONG">0200539E</e:Longitude></e:Designated-point>
<e:Designated-point id = "PERIT">
<e:Designated-point-ident id = "ENR44100413113637206">PERIT</e:Designated-point-ident>
<e:Latitude id = "PERIT-LAT">474718N</e:Latitude>
<e:Longitude id = "PERIT-LONG">0213722E</e:Longitude></e:Designated-point>
<e:Designated-point id = "PESAT">
<e:Designated-point-ident id = "ENR43090225142432189">PESAT</e:Designated-point-ident>
<e:Latitude id = "PESAT-LAT">474254N</e:Latitude>
<e:Longitude id = "PESAT-LONG">0170311E</e:Longitude></e:Designated-point>
<e:Designated-point id = "PIDON">
<e:Designated-point-ident id = "ENR44100413113637210">PIDON</e:Designated-point-ident>
<e:Latitude id = "PIDON-LAT">460720N</e:Latitude>
<e:Longitude id = "PIDON-LONG">0180410E</e:Longitude></e:Designated-point>
<e:Designated-point id = "PITOK">
<e:Designated-point-ident id = "ENR44100413113637214">PITOK</e:Designated-point-ident>
<e:Latitude id = "PITOK-LAT">481929N</e:Latitude>
<e:Longitude id = "PITOK-LONG">0202218E</e:Longitude></e:Designated-point>
<e:Designated-point id = "PUSTA">
<e:Designated-point-ident id = "ENR44100413113637218">PUSTA</e:Designated-point-ident>
<e:Latitude id = "PUSTA-LAT">470908N</e:Latitude>
<e:Longitude id = "PUSTA-LONG">0184432E</e:Longitude></e:Designated-point>
<e:Designated-point id = "RIGSA">
<e:Designated-point-ident id = "ENR44100413113637222">RIGSA</e:Designated-point-ident>
<e:Latitude id = "RIGSA-LAT">480952N</e:Latitude>
<e:Longitude id = "RIGSA-LONG">0204506E</e:Longitude></e:Designated-point>
<e:Designated-point id = "ROMKA">
<e:Designated-point-ident id = "ENR44100413113637226">ROMKA</e:Designated-point-ident>
<e:Latitude id = "ROMKA-LAT">481319N</e:Latitude>
<e:Longitude id = "ROMKA-LONG">0215025E</e:Longitude></e:Designated-point>
<e:Designated-point id = "SASAL">
<e:Designated-point-ident id = "ENR43090225142432208"><?FM MARKER [FrameAPS Content] CM-3.1,262144,655360?>SASAL</e:Designated-point-ident>
<e:Latitude id = "SASAL-LAT">471705N</e:Latitude>
<e:Longitude id = "SASAL-LONG">0162828E</e:Longitude></e:Designated-point>
<e:Designated-point id = "SIRDU">
<e:Designated-point-ident id = "ENR44100413113637234">SIRDU</e:Designated-point-ident>
<e:Latitude id = "SIRDU-LAT">471517N</e:Latitude>
<e:Longitude id = "SIRDU-LONG">0171955E</e:Longitude></e:Designated-point>
<e:Designated-point id = "SOGMO">
<e:Designated-point-ident id = "ENR44100413113637238">SOGMO</e:Designated-point-ident>
<e:Latitude id = "SOGMO-LAT">463637N</e:Latitude>
<e:Longitude id = "SOGMO-LONG">0174103E</e:Longitude></e:Designated-point>
<e:Designated-point id = "SOPRO">
<e:Designated-point-ident id = "ENR44100413113637246">SOPRO</e:Designated-point-ident>
<e:Latitude id = "SOPRO-LAT">473516N</e:Latitude>
<e:Longitude id = "SOPRO-LONG">0164809E</e:Longitude></e:Designated-point>
<e:Designated-point id = "STEIN">
<e:Designated-point-ident id = "ENR43090225142432224">STEIN</e:Designated-point-ident>
<e:Latitude id = "STEIN-LAT">472539N</e:Latitude>
<e:Longitude id = "STEIN-LONG">0163559E</e:Longitude></e:Designated-point>
<e:Designated-point id = "SUBES">
<e:Designated-point-ident id = "ENR44100413113637254">SUBES</e:Designated-point-ident>
<e:Latitude id = "SUBES-LAT">472516N</e:Latitude>
<e:Longitude id = "SUBES-LONG">0172536E</e:Longitude></e:Designated-point>
<e:Designated-point id = "SUNIS">
<e:Designated-point-ident id = "ENR43090225142432230">SUNIS</e:Designated-point-ident>
<e:Latitude id = "SUNIS-LAT">470831N</e:Latitude>
<e:Longitude id = "SUNIS-LONG">0162059E</e:Longitude></e:Designated-point>
<e:Designated-point id = "SUNOR">
<e:Designated-point-ident id = "ENR44100413113637258">SUNOR</e:Designated-point-ident>
<e:Latitude id = "SUNOR-LAT">462847N</e:Latitude>
<e:Longitude id = "SUNOR-LONG">0171750E</e:Longitude></e:Designated-point>
<e:Designated-point id = "TEGRI">
<e:Designated-point-ident id = "ENR43090225142432237">TEGRI</e:Designated-point-ident>
<e:Latitude id = "TEGRI-LAT">461546N</e:Latitude>
<e:Longitude id = "TEGRI-LONG">0210616E</e:Longitude></e:Designated-point>
<e:Designated-point id = "TEKNO">
<e:Designated-point-ident id = "ENR44100413113637266">TEKNO</e:Designated-point-ident>
<e:Latitude id = "TEKNO-LAT">473726N</e:Latitude>
<e:Longitude id = "TEKNO-LONG">0172432E</e:Longitude></e:Designated-point>
<e:Designated-point id = "TONDO">
<e:Designated-point-ident id = "ENR43090225142432243">TONDO</e:Designated-point-ident>
<e:Latitude id = "TONDO-LAT">460250N</e:Latitude>
<e:Longitude id = "TONDO-LONG">0192121E</e:Longitude></e:Designated-point>
<e:Designated-point id = "TORNO">
<e:Designated-point-ident id = "ENR44100413113637270">TORNO</e:Designated-point-ident>
<e:Latitude id = "TORNO-LAT">473223N</e:Latitude>
<e:Longitude id = "TORNO-LONG">0182924E</e:Longitude></e:Designated-point>
<e:Designated-point id = "VAMOG">
<e:Designated-point-ident id = "ENR44100413113637278">VAMOG</e:Designated-point-ident>
<e:Latitude id = "VAMOG-LAT">474714N</e:Latitude>
<e:Longitude id = "VAMOG-LONG">0173945E</e:Longitude></e:Designated-point>
<e:Designated-point id = "VEBAL">
<e:Designated-point-ident id = "ENR44100413113637282">VEBAL</e:Designated-point-ident>
<e:Latitude id = "VEBAL-LAT">455929N</e:Latitude>
<e:Longitude id = "VEBAL-LONG">0171748E</e:Longitude></e:Designated-point>
<e:Designated-point id = "VEBOS">
<e:Designated-point-ident id = "ENR44100413113637286">VEBOS</e:Designated-point-ident>
<e:Latitude id = "VEBOS-LAT">471823N</e:Latitude>
<e:Longitude id = "VEBOS-LONG">0183814E</e:Longitude></e:Designated-point>
<e:Designated-point id = "VERIG">
<e:Designated-point-ident id = "ENR44100413113637290">VERIG</e:Designated-point-ident>
<e:Latitude id = "VERIG-LAT">471020N</e:Latitude>
<e:Longitude id = "VERIG-LONG">0214329E</e:Longitude></e:Designated-point>
<e:Designated-point id = "XOMBA">
<e:Designated-point-ident id = "ENR43090225142432262">XOMBA</e:Designated-point-ident>
<e:Latitude id = "XOMBA-LAT">474524N</e:Latitude>
<e:Longitude id = "XOMBA-LONG">0180343E</e:Longitude></e:Designated-point>
</e:Designated-point-table><?FM MARKER [FrameAPS Content] PU-0.1,24894339,1595223?>
</e:ENR-4.4>
